{
  "$schema": "https://mintlify.com/schema.json",
  "name": "lloyal-agents",
  "logo": {
    "dark": "/logo/dark.svg",
    "light": "/logo/light.svg"
  },
  "favicon": "/favicon.svg",
  "colors": {
    "primary": "#10B981",
    "light": "#34D399",
    "dark": "#059669",
    "background": {
      "dark": "#111111"
    },
    "anchors": {
      "from": "#10B981",
      "to": "#34D399"
    }
  },
  "font": {
    "headings": { "family": "Quicksand", "weight": 600 },
    "body": { "family": "Quicksand", "weight": 400 }
  },
  "modeToggle": {
    "default": "dark"
  },
  "topbarLinks": [
    {
      "name": "GitHub",
      "url": "https://github.com/lloyal-ai/sdk"
    }
  ],
  "topbarCtaButton": {
    "name": "npm",
    "url": "https://www.npmjs.com/package/@lloyal-labs/lloyal-agents"
  },
  "tabs": [
    { "name": "Get Started", "url": "learn" },
    { "name": "Reference", "url": "reference" },
    { "name": "Guides", "url": "guides" },
    { "name": "Examples", "url": "examples" },
    { "name": "API", "url": "https://lloyal-ai.github.io/sdk/" }
  ],
  "navigation": [
    {
      "group": "Get Started",
      "pages": [
        "learn/introduction",
        "learn/quick-start",
        "learn/thinking-in-lloyal",
        "learn/tools",
        "learn/agents",
        "learn/sources",
        "learn/pipelines",
        "learn/sessions",
        "learn/tracing"
      ]
    },
    {
      "group": "Core",
      "pages": [
        "reference/concurrency",
        "reference/kv-pressure",
        "reference/prefix-sharing",
        "reference/grammar-and-ordering",
        "reference/scratchpad-extraction",
        "reference/prompt-composition",
        "reference/branch-lifecycle"
      ]
    },
    {
      "group": "RIG",
      "pages": [
        "reference/rig/overview",
        "reference/rig/corpus-source",
        "reference/rig/web-source",
        "reference/rig/custom-sources",
        "reference/rig/bridges",
        "reference/rig/deep-research"
      ]
    },
    {
      "group": "Guides",
      "pages": [
        "guides/custom-tool",
        "guides/custom-source",
        "guides/custom-pipeline",
        "guides/deployment"
      ]
    },
    {
      "group": "Examples",
      "pages": [
        "examples/react-agent",
        "examples/reflection",
        "examples/supervisor",
        "examples/deep-research"
      ]
    }
  ],
  "footerSocials": {
    "github": "https://github.com/lloyal-ai/sdk"
  }
}
